django_redux/__init__.py
django_redux/consumers.py
django_redux/engine.py
django_redux/routing.py
django_redux/tests.py
django_redux/static/.DS_Store
django_redux/static/django_redux/.DS_Store
django_redux/static/django_redux/.babelrc
django_redux/static/django_redux/.eslintrc.js
django_redux/static/django_redux/.npmignore
django_redux/static/django_redux/README.md
django_redux/static/django_redux/esdoc.json
django_redux/static/django_redux/package.json
django_redux/static/django_redux/docs/badge.svg
django_redux/static/django_redux/docs/coverage.json
django_redux/static/django_redux/docs/dump.json
django_redux/static/django_redux/docs/identifiers.html
django_redux/static/django_redux/docs/index.html
django_redux/static/django_redux/docs/package.json
django_redux/static/django_redux/docs/source.html
django_redux/static/django_redux/docs/ast/source/index.js.json
django_redux/static/django_redux/docs/class/src/index.js~ReduxBridge.html
django_redux/static/django_redux/docs/class/src/index.js~WebSocketBridge.html
django_redux/static/django_redux/docs/css/prettify-tomorrow.css
django_redux/static/django_redux/docs/css/style.css
django_redux/static/django_redux/docs/file/src/index.js.html
django_redux/static/django_redux/docs/image/badge.svg
django_redux/static/django_redux/docs/image/esdoc-logo-mini-black.png
django_redux/static/django_redux/docs/image/esdoc-logo-mini.png
django_redux/static/django_redux/docs/image/github.png
django_redux/static/django_redux/docs/image/manual-badge.svg
django_redux/static/django_redux/docs/image/search.png
django_redux/static/django_redux/docs/script/inherited-summary.js
django_redux/static/django_redux/docs/script/inner-link.js
django_redux/static/django_redux/docs/script/manual.js
django_redux/static/django_redux/docs/script/patch-for-local.js
django_redux/static/django_redux/docs/script/pretty-print.js
django_redux/static/django_redux/docs/script/search.js
django_redux/static/django_redux/docs/script/search_index.js
django_redux-1.0.0.dist-info/LICENSE
django_redux-1.0.0.dist-info/METADATA
django_redux-1.0.0.dist-info/WHEEL
django_redux-1.0.0.dist-info/top_level.txt
django_redux-1.0.0.dist-info/RECORD
