Metadata-Version: 2.1
Name: django-redux
Version: 1.0.0
Summary: A re-usable bridge between Django channels and Redux Edit
Home-page: https://github.com/channels-frontend/django_redux
Author: Flavio Curella
Author-email: flavio.curella@gmail.com
License: UNKNOWN
Platform: UNKNOWN
Classifier: Development Status :: 4 - Beta
Classifier: Environment :: Web Environment
Classifier: Intended Audience :: Developers
Classifier: Operating System :: OS Independent
Classifier: Programming Language :: Python :: 2
Classifier: Programming Language :: Python :: 3
Classifier: Framework :: Django
Requires-Dist: channels
Requires-Dist: Django
